Workbook

Sheet Lisez-moi
A1: Registre des risques — NotAge
A3: Référence | B3: NTG-SMSI-RSK-002
A4: Version | B4: 1.0
A5: Date | B5: 27/09/2026
A6: Propriétaire | B6: RSSI
A7: Approbateur | B7: Direction générale (CEO)
A8: Classification | B8: Confidentiel (publié à titre de démonstration, entreprise fictive)
A9: Méthode | B9: ISO/IEC 27005:2022 — voir NTG-SMSI-RSK-001
A10: Exigences couvertes | B10: ISO/IEC 27001:2022, articles 6.1.2 et 8.2
A12: Mode d'emploi
A13: Feuille Échelles | B13: Échelles de gravité et de vraisemblance, matrice des niveaux de risque et critères d'acceptation.
A14: Feuille Registre | B14: Les 12 scénarios de risque. Chaque ligne décrit la source, le scénario, les actifs concernés, les vulnérabilités, les mesures existantes et l'évaluation.
A15: Cellules à saisir | B15: Gravité (G) et vraisemblance (V), en bleu : valeurs entières de 1 à 4. Toute autre valeur est refusée.
A16: Cellules calculées | B16: Niveau de risque = G × V (de 1 à 16) et zone (Faible, Modéré, Élevé, Critique) : formules, ne pas saisir.
A17: Feuille Cartographie | B17: Nombre de scénarios par case de la matrice et par zone, recalculé automatiquement.
A18: Risque initial | B18: Niveau évalué en tenant compte des mesures déjà en place en septembre 2026, avant tout traitement.

Sheet Échelles
A1: Échelle de gravité (G)
A2: Niveau | B2: Libellé | C2: Financier | D2: Clients et contrats | E2: Juridique et réglementaire | F2: Image et opérations
A3: 1 | B3: Mineure | C3: Moins de 10 k€ | D3: Aucun client affecté de façon notable | E3: Aucune conséquence | F3: Gêne interne, sans effet visible
A4: 2 | B4: Significative | C4: 10 à 100 k€ | D4: Quelques clients gênés, interruption de moins de 4 h hors clôture | E4: Aucune notification requise | F4: Mécontentement ponctuel
A5: 3 | B5: Grave | C5: 100 k€ à 1 M€ | D5: Plusieurs clients affectés, interruption de 4 à 24 h ou en clôture, manquement contractuel | E5: Violation de données notifiable de portée limitée | F5: Plaintes, couverture médiatique locale
A6: 4 | B6: Critique | C6: Plus de 1 M€ | D6: Perte d'un client majeur, interruption de plus de 24 h | E6: Violation massive, sanction de la CNIL | F6: Atteinte durable à la réputation, pérennité menacée
A7: La gravité retenue est la plus élevée parmi les quatre dimensions.
A9: Échelle de vraisemblance (V)
A10: Niveau | B10: Libellé | C10: Définition
A11: 1 | B11: Peu vraisemblable | C11: Source de risque peu motivée ou peu capable, mesures existantes solides. Non attendu sur les trois prochaines années.
A12: 2 | B12: Vraisemblable | C12: Scénario déjà observé dans le secteur, mais qui suppose des moyens ou des circonstances particuliers. Possible sur trois ans.
A13: 3 | B13: Très vraisemblable | C13: Menace active contre ce type d'entreprise, vulnérabilités connues, peu de mesures. Attendu dans l'année.
A14: 4 | B14: Quasi certain | C14: Se produit déjà, ou plusieurs fois par an.
A17: Matrice des niveaux de risque (niveau = G × V)
A18: V \ G | B18: 1 | C18: 2 | D18: 3 | E18: 4
A19: 4 | B19: =B$18*$A19 -> 4 | C19: =C$18*$A19 -> 8 | D19: =D$18*$A19 -> 12 | E19: =E$18*$A19 -> 16
A20: 3 | B20: =B$18*$A20 -> 3 | C20: =C$18*$A20 -> 6 | D20: =D$18*$A20 -> 9 | E20: =E$18*$A20 -> 12
A21: 2 | B21: =B$18*$A21 -> 2 | C21: =C$18*$A21 -> 4 | D21: =D$18*$A21 -> 6 | E21: =E$18*$A21 -> 8
A22: 1 | B22: =B$18*$A22 -> 1 | C22: =C$18*$A22 -> 2 | D22: =D$18*$A22 -> 3 | E22: =E$18*$A22 -> 4
A24: Zones et critères d'acceptation
A25: Niveau | B25: Zone | C25: Décision attendue | D25: Qui peut accepter le risque résiduel
A26: 12 à 16 | B26: Critique | C26: Traitement prioritaire obligatoire, plan d'action sous 3 mois | D26: Non acceptable en l'état
A27: 8 à 9 | B27: Élevé | C27: Traitement requis, plan d'action sous 6 mois | D27: Direction générale uniquement, avec justification écrite
A28: 4 à 6 | B28: Modéré | C28: Traitement si le coût est raisonnable, sinon acceptation | D28: Propriétaire du risque
A29: 1 à 3 | B29: Faible | C29: Acceptation, surveillance lors de la revue annuelle | D29: Propriétaire du risque
A31: Critère d'acceptation cible : tout risque résiduel doit être au plus Modéré (≤ 6), ou Élevé avec acceptation écrite de la direction.

Sheet Registre
A1: Registre des risques NotAge — appréciation et traitement (septembre 2026)
A2: Saisir uniquement les G et V initiaux et résiduels (en bleu, de 1 à 4). Niveaux et zones sont calculés. Méthode : NTG-SMSI-RSK-001 ; plan : NTG-SMSI-RSK-004.
A3: APPRÉCIATION DU RISQUE INITIAL | Q3: TRAITEMENT ET RISQUE RÉSIDUEL
A4: ID | B4: Scénario | C4: Source de risque | D4: Description du scénario | E4: Actifs primordiaux | F4: Actifs supports | G4: Critère DIC | H4: Vulnérabilités | I4: Mesures existantes | J4: Gravité (G) | K4: Justification de la gravité | L4: Vraisemblance (V) | M4: Justification de la vraisemblance | N4: Niveau initial (G × V) | O4: Zone initiale | P4: Propriétaire du risque | Q4: Option de traitement | R4: Mesures de l'annexe A | S4: Actions principales | T4: Responsable de la mise en œuvre | U4: Échéance | V4: G résiduelle | W4: V résiduelle | X4: Niveau résiduel | Y4: Zone résiduelle | Z4: Acceptation du risque résiduel
A5: R01 | B5: Détournement de paiements par modification frauduleuse d'un IBAN fournisseur | C5: Groupe cybercriminel spécialisé dans la fraude au virement | D5: L'attaquant obtient les identifiants d'un utilisateur d'une entreprise cliente (hameçonnage ou mot de passe réutilisé), se connecte à NotAge et remplace l'IBAN d'un fournisseur. Le fichier de virement suivant, validé sans vérification particulière, envoie les paiements sur son compte. | E5: AP2, AP5 | F5: AS04, AS06 | G5: I | H5: Authentification multifacteur non imposée aux utilisateurs clients ; modification d'IBAN sans contrôle renforcé ni notification ; aucune détection des comportements anormaux | I5: Journal applicatif basique ; circuit de validation des factures (qui ne couvre pas le changement d'IBAN) | J5: 4 | K5: Fraude pouvant atteindre plusieurs centaines de milliers d'euros chez un client, mise en cause de NotAge, perte probable du client | L5: 3 | M5: Fraude très active en France, vecteur simple, aucune mesure ne bloque la modification | N5: =J5*L5 -> 12 | O5: =IF(N5>=12,"Critique",IF(N5>=8,"Élevé",IF(N5>=4,"Modéré","Faible"))) -> Critique | P5: CFO | Q5: Réduire | R5: 8.26, 8.5, 8.15, 8.16 | S5: • Double validation de toute modification d'IBAN par deux utilisateurs distincts du client, avec notification au fournisseur et à l'administrateur du client (8.26) • Authentification multifacteur obligatoire pour les rôles administrateur et valideur des clients, réauthentification avant toute action sensible (8.5) • Journal inaltérable des modifications de coordonnées bancaires : auteur, date, ancienne et nouvelle valeur (8.15) • Détection des comportements anormaux (connexion inhabituelle suivie d'un changement d'IBAN) avec alerte au client et au support (8.16) | T5: CTO | U5: 31/12/2026 | V5: 4 | W5: 1 | X5: =V5*W5 -> 4 | Y5: =IF(X5>=12,"Critique",IF(X5>=8,"Élevé",IF(X5>=4,"Modéré","Faible"))) -> Modéré | Z5: Acceptée par le CFO
A6: R02 | B6: Chiffrement ou destruction de la production par rançongiciel après compromission d'un compte administrateur AWS | C6: Groupe cybercriminel (rançongiciel) | D6: L'attaquant vole les accès de l'un des dix comptes à privilèges étendus (hameçonnage, clé d'accès exposée sur un poste). Il chiffre ou supprime les bases et le stockage, efface les sauvegardes accessibles avec les mêmes droits, puis exige une rançon. | E6: AP1 à AP5 | F6: AS01, AS02, AS06, AS12 | G6: D, I | H6: Droits d'administration étendus à dix personnes sans revue ; sauvegardes supprimables avec les mêmes droits et restauration jamais testée ; pas de surveillance centralisée ; pas de procédure de réponse aux incidents | I6: Authentification multifacteur sur la console via le SSO (pas sur les clés d'accès programmatiques) ; sauvegardes automatiques répliquées dans une autre région | J6: 4 | K6: Arrêt complet du service pour tous les clients pendant plusieurs jours, perte de données possible, manquement contractuel généralisé | L6: 3 | M6: Les rançongiciels ciblent massivement les PME ; dix comptes à privilèges sans revue multiplient les points d'entrée | N6: =J6*L6 -> 12 | O6: =IF(N6>=12,"Critique",IF(N6>=8,"Élevé",IF(N6>=4,"Modéré","Faible"))) -> Critique | P6: CTO | Q6: Réduire et partager | R6: 8.2, 5.18, 8.5, 8.13, 8.16, 5.24, 5.26 | S6: • Deux administrateurs permanents seulement, élévation temporaire de privilèges sur demande, suppression des clés d'accès de longue durée (8.2) • Revue trimestrielle des droits d'accès à l'environnement AWS (5.18) • Clés de sécurité physiques pour tous les comptes à privilèges (8.5) • Sauvegardes chiffrées et immuables dans un compte AWS séparé, test de restauration chaque trimestre (8.13) • Journalisation centralisée et alertes sur les actions sensibles : suppression, modification des droits (8.16) • Procédure de gestion des incidents et exercice annuel de crise rançongiciel (5.24, 5.26) • Partage : l'assurance cyber couvre une partie des pertes d'exploitation et des frais de réponse | T6: Responsable infrastructure | U6: 31/12/2026 | V6: 3 | W6: 2 | X6: =V6*W6 -> 6 | Y6: =IF(X6>=12,"Critique",IF(X6>=8,"Élevé",IF(X6>=4,"Modéré","Faible"))) -> Modéré | Z6: Acceptée par le CTO
A7: R03 | B7: Vol massif de données par exploitation d'une vulnérabilité de l'application | C7: Cybercriminels (revente de données, extorsion) | D7: Un attaquant exploite une vulnérabilité de l'application ou de l'API, par exemple un défaut de cloisonnement entre clients relevé lors du test d'intrusion de 2025 et non corrigé, pour extraire en masse justificatifs, identités et IBAN d'autres clients. | E7: AP1, AP3 | F7: AS04, AS05 | G7: C | H7: Vulnérabilités du test d'intrusion de 2025 pas toutes corrigées ; pas de processus de gestion des vulnérabilités ; pas de tests de sécurité automatisés dans la chaîne CI/CD ; pas de règles de codage sécurisé formalisées | I7: Revue de code systématique ; pare-feu applicatif | J7: 4 | K7: Violation massive de données personnelles, notification par tous les clients à la CNIL, sanctions possibles, atteinte durable à l'image | L7: 3 | M7: Vulnérabilités connues et non corrigées sur une application exposée sur Internet | N7: =J7*L7 -> 12 | O7: =IF(N7>=12,"Critique",IF(N7>=8,"Élevé",IF(N7>=4,"Modéré","Faible"))) -> Critique | P7: CTO | Q7: Réduire | R7: 8.8, 8.28, 8.29 | S7: • Correction de toutes les vulnérabilités critiques et élevées du test d'intrusion de 2025 avant fin 2026, puis délais de correction par criticité : 15 jours pour les critiques, 30 jours pour les élevées (8.8) • Règles de codage sécurisé fondées sur l'OWASP, formation annuelle des développeurs, contrôle des dépendances (8.28) • Analyse automatique du code et des dépendances dans la CI, test d'intrusion annuel ciblant le cloisonnement entre clients (8.29) | T7: CTO | U7: 31/12/2026 (corrections), 31/03/2027 (outillage) | V7: 4 | W7: 2 | X7: =V7*W7 -> 8 | Y7: =IF(X7>=12,"Critique",IF(X7>=8,"Élevé",IF(X7>=4,"Modéré","Faible"))) -> Élevé | Z7: Risque résiduel élevé accepté par écrit par la direction générale jusqu'au test d'intrusion de mars 2027
A8: R04 | B8: Exposition publique de justificatifs par erreur de configuration du stockage cloud | C8: Erreur interne non intentionnelle | D8: Lors d'une évolution, un espace de stockage de justificatifs ou un instantané de base de données est rendu accessible publiquement. L'exposition est découverte par un chercheur en sécurité ou par un attaquant qui scanne Internet. | E8: AP1 | F8: AS01 | G8: C | H8: Pas de référentiel de configuration sécurisée ni de contrôle automatique des configurations ; infrastructure modifiée manuellement par plusieurs personnes ; aucune alerte en cas de changement risqué | I8: Chiffrement au repos (sans effet en cas d'exposition publique) | J8: 4 | K8: Exposition potentielle de l'ensemble des justificatifs des utilisateurs, violation de données notifiable | L8: 2 | M8: Erreur fréquente dans le secteur, mais qui suppose un changement de configuration malheureux | N8: =J8*L8 -> 8 | O8: =IF(N8>=12,"Critique",IF(N8>=8,"Élevé",IF(N8>=4,"Modéré","Faible"))) -> Élevé | P8: CTO | Q8: Réduire | R8: 8.9, 5.23, 8.16 | S8: • Infrastructure décrite en code, configurations de référence (blocage de l'accès public, chiffrement), revue de chaque changement (8.9) • Règles d'utilisation d'AWS : responsabilité partagée, services autorisés, contrôle continu de la posture de sécurité (5.23) • Alerte immédiate en cas d'exposition publique d'une ressource (8.16) | T8: Responsable infrastructure | U8: 31/03/2027 | V8: 4 | W8: 1 | X8: =V8*W8 -> 4 | Y8: =IF(X8>=12,"Critique",IF(X8>=8,"Élevé",IF(X8>=4,"Modéré","Faible"))) -> Modéré | Z8: Acceptée par le CTO
A9: R05 | B9: Injection de code malveillant ou vol de secrets via la chaîne de développement | C9: Cybercriminels (attaque de la chaîne d'approvisionnement logicielle) | D9: L'attaquant compromet le compte GitHub d'un développeur ou une dépendance tierce. Il fait déployer du code malveillant en production ou récupère les secrets de production présents dans le code et la chaîne CI/CD. | E9: AP6, AP4 | F9: AS05, AS13 | G9: I, C | H9: Secrets présents dans le code et les variables de la CI ; authentification multifacteur GitHub non imposée à tous ; dépendances et actions tierces non contrôlées ; protections de branches incomplètes | I9: Revue de code systématique avant fusion | J9: 4 | K9: Code compromis distribué à tous les clients, accès complet à la production | L9: 2 | M9: Attaques de ce type en forte hausse, mais plus exigeantes techniquement ; la revue de code freine l'injection directe | N9: =J9*L9 -> 8 | O9: =IF(N9>=12,"Critique",IF(N9>=8,"Élevé",IF(N9>=4,"Modéré","Faible"))) -> Élevé | P9: CTO | Q9: Réduire | R9: 8.4, 5.17, 8.32, 8.28 | S9: • Authentification multifacteur obligatoire sur GitHub, accès au code selon le besoin, branches protégées (8.4) • Retrait des secrets du code, stockage dans un coffre, rotation des secrets exposés, détection automatique dans la CI (5.17) • Déploiement en production uniquement par la CI, après validation d'une seconde personne (8.32) • Contrôle des dépendances et des actions tierces utilisées dans la CI (8.28) | T9: CTO | U9: 31/03/2027 | V9: 4 | W9: 1 | X9: =V9*W9 -> 4 | Y9: =IF(X9>=12,"Critique",IF(X9>=8,"Élevé",IF(X9>=4,"Modéré","Faible"))) -> Modéré | Z9: Acceptée par le CTO
A10: R06 | B10: Consultation ou modification abusive de données clients par un membre du support | C10: Salarié malveillant ou manipulé (interne) | D10: Un agent du support, qui dispose d'un accès complet au back-office, consulte des données sans besoin (curiosité, revente) ou modifie des coordonnées à la demande d'un faux client (ingénierie sociale). | E10: AP1 à AP3 | F10: AS14, AS04 | G10: C, I | H10: Accès au back-office non limité aux dossiers traités ; IBAN affichés en clair ; consultations ni journalisées ni revues | I10: Clause de confidentialité dans les contrats de travail | J10: 3 | K10: Atteinte aux données de plusieurs clients, possible complicité de fraude | L10: 2 | M10: Équipe de huit personnes de confiance, mais aucune barrière technique ni traçabilité | N10: =J10*L10 -> 6 | O10: =IF(N10>=12,"Critique",IF(N10>=8,"Élevé",IF(N10>=4,"Modéré","Faible"))) -> Modéré | P10: Responsable relation client | Q10: Réduire | R10: 8.3, 8.11, 8.15 | S10: • Accès du support limité aux comptes des clients ayant ouvert une demande (8.3) • IBAN masqués dans le back-office, seuls les quatre derniers caractères visibles (8.11) • Journalisation des consultations et revue mensuelle par échantillonnage (8.15) | T10: CTO | U10: 31/03/2027 | V10: 3 | W10: 1 | X10: =V10*W10 -> 3 | Y10: =IF(X10>=12,"Critique",IF(X10>=8,"Élevé",IF(X10>=4,"Modéré","Faible"))) -> Faible | Z10: Acceptée par le responsable relation client
A11: R07 | B11: Utilisation du compte d'un ancien salarié resté actif | C11: Ancien salarié mécontent, ou attaquant réutilisant des identifiants | D11: Les comptes d'un salarié parti (Google Workspace, AWS, GitHub, outils SaaS) n'ont pas tous été désactivés. Ils sont utilisés pour accéder à des données internes ou clients. | E11: AP1, AP6, AP7 | F11: AS06 | G11: C | H11: Départs gérés sans procédure ni liste des accès à retirer ; pas de revue périodique des comptes ; plusieurs outils SaaS hors du SSO | I11: Désactivation du compte Google à la demande des RH, de façon irrégulière | J11: 3 | K11: Accès non autorisé à des données clients ou au code | L11: 3 | M11: Comptes orphelins déjà constatés à l'arrivée de la RSSI ; vingt départs et arrivées attendus avec la croissance | N11: =J11*L11 -> 9 | O11: =IF(N11>=12,"Critique",IF(N11>=8,"Élevé",IF(N11>=4,"Modéré","Faible"))) -> Élevé | P11: Responsable RH | Q11: Réduire | R11: 5.16, 5.18, 6.5 | S11: • Procédure d'arrivée et de départ avec la liste des accès par profil, tous les outils raccordés au SSO, désactivation le jour du départ (5.16) • Revue trimestrielle des comptes et des droits (5.18) • Rappel écrit des obligations de confidentialité et restitution du matériel au départ (6.5) | T11: Responsable RH et responsable informatique interne | U11: 31/12/2026 | V11: 3 | W11: 1 | X11: =V11*W11 -> 3 | Y11: =IF(X11>=12,"Critique",IF(X11>=8,"Élevé",IF(X11>=4,"Modéré","Faible"))) -> Faible | Z11: Acceptée par la responsable RH
A12: R08 | B12: Interruption prolongée du service en période de clôture comptable | C12: Erreur humaine (déploiement), défaillance technique ou panne d'un service AWS | D12: Une mise en production défaillante corrompt des données ou rend la plateforme indisponible en fin de mois. Faute de procédure de retour arrière et de restauration éprouvée, l'interruption dure plusieurs heures en pleine clôture. | E12: AP4, AP5 | F12: AS01, AS02, AS04, AS05 | G12: D, I | H12: Pas de plan de continuité ni de reprise ; restauration jamais testée ; gestion des changements informelle, sans plan de retour arrière ; objectifs de reprise non définis | I12: Plateforme répartie sur plusieurs zones de disponibilité AWS ; sauvegardes automatiques | J12: 3 | K12: Engagement de disponibilité de 99,9 % rompu, clôtures des clients retardées, pénalités possibles | L12: 3 | M12: Plusieurs mises en production par semaine sans filet ; un incident de ce type est attendu dans l'année | N12: =J12*L12 -> 9 | O12: =IF(N12>=12,"Critique",IF(N12>=8,"Élevé",IF(N12>=4,"Modéré","Faible"))) -> Élevé | P12: CTO | Q12: Réduire | R12: 5.30, 8.13, 8.32 | S12: • Objectifs de reprise fixés (reprise en 4 heures, perte de données d'une heure au plus), plan de reprise testé chaque année (5.30) • Tests de restauration trimestriels (8.13, mesure partagée avec R02) • Plan de retour arrière obligatoire, gel des mises en production majeures pendant les clôtures, déploiements progressifs (8.32) | T12: CTO | U12: 31/03/2027 | V12: 2 | W12: 2 | X12: =V12*W12 -> 4 | Y12: =IF(X12>=12,"Critique",IF(X12>=8,"Élevé",IF(X12>=4,"Modéré","Faible"))) -> Modéré | Z12: Acceptée par le CTO
A13: R09 | B13: Compromission d'un compte de messagerie par hameçonnage ciblé | C13: Cybercriminels | D13: Une fausse page de connexion Google capture l'identifiant et le code de double authentification d'un salarié (attaque par relais). L'attaquant accède à ses e-mails et documents (contrats, exports clients) et s'en sert pour hameçonner des clients au nom de NotAge. | E13: AP7, AP1 | F13: AS07, AS09 | G13: C | H13: Aucune sensibilisation des salariés ; pas de procédure de signalement ; double authentification par code, non résistante au hameçonnage | I13: Authentification multifacteur sur Google Workspace ; filtrage anti-spam natif | J13: 3 | K13: Fuite de documents internes et clients, rebond possible vers les clients | L13: 2 | M13: Hameçonnage omniprésent, mais la double authentification impose une attaque plus élaborée | N13: =J13*L13 -> 6 | O13: =IF(N13>=12,"Critique",IF(N13>=8,"Élevé",IF(N13>=4,"Modéré","Faible"))) -> Modéré | P13: Direction générale (CEO) | Q13: Réduire | R13: 6.3, 6.8 | S13: • Sensibilisation à l'arrivée puis annuelle, campagnes trimestrielles d'hameçonnage simulé (6.3) • Canal de signalement unique (bouton dans la messagerie et canal Slack dédié) et réponse de la RSSI sous 1 heure ouvrée (6.8) | T13: RSSI | U13: 31/12/2026 | V13: 2 | W13: 2 | X13: =V13*W13 -> 4 | Y13: =IF(X13>=12,"Critique",IF(X13>=8,"Élevé",IF(X13>=4,"Modéré","Faible"))) -> Modéré | Z13: Acceptée par la direction générale
A14: R10 | B14: Perte ou vol d'un ordinateur portable ou d'un smartphone personnel | C14: Vol opportuniste ou perte | D14: Un smartphone personnel sans code de verrouillage, qui donne accès à la messagerie et à Slack (où circulent des captures de données clients), est volé. Ou un portable est perdu avec des sessions ouvertes. | E14: AP7, AP1 | F14: AS09, AS10 | G14: C | H14: Smartphones personnels non gérés (pas de code imposé, pas d'effacement à distance) ; pas de gestion centralisée des postes ; pas de règles pour les déplacements | I14: Disques des ordinateurs portables chiffrés | J14: 2 | K14: Exposition limitée aux données présentes sur l'appareil | L14: 3 | M14: Perte ou vol d'appareil très fréquent avec 50 salariés en télétravail et en déplacement | N14: =J14*L14 -> 6 | O14: =IF(N14>=12,"Critique",IF(N14>=8,"Élevé",IF(N14>=4,"Modéré","Faible"))) -> Modéré | P14: CTO | Q14: Réduire | R14: 8.1, 7.9 | S14: • Gestion centralisée des portables (chiffrement vérifié, verrouillage, effacement à distance) et accès mobile uniquement via un profil professionnel protégé (8.1) • Règles pour les déplacements et déclaration de toute perte sous 24 heures (7.9) | T14: Responsable informatique interne | U14: 31/03/2027 | V14: 1 | W14: 3 | X14: =V14*W14 -> 3 | Y14: =IF(X14>=12,"Critique",IF(X14>=8,"Élevé",IF(X14>=4,"Modéré","Faible"))) -> Faible | Z14: Acceptée par le CTO
A15: R11 | B15: Fuite de données clients via un fournisseur SaaS compromis | C15: Cybercriminels ciblant un fournisseur | D15: L'outil de support (dont les tickets contiennent des captures et des IBAN) ou le prestataire d'envoi d'e-mails transactionnels est compromis. Il en résulte une fuite de données clients ou l'envoi d'e-mails frauduleux au nom de NotAge. | E15: AP1 | F15: AS08, AS16 | G15: C, I | H15: Fournisseurs jamais évalués ; contrats sans clauses de sécurité ni obligation de notifier les incidents ; données sensibles copiées sans nécessité dans les tickets | I15: Aucune mesure spécifique | J15: 3 | K15: Violation de données notifiable, manquement aux clauses DORA des clients financiers | L15: 2 | M15: Attaques contre les éditeurs SaaS en hausse ; fournisseurs établis mais non évalués | N15: =J15*L15 -> 6 | O15: =IF(N15>=12,"Critique",IF(N15>=8,"Élevé",IF(N15>=4,"Modéré","Faible"))) -> Modéré | P15: CFO | Q15: Réduire | R15: 5.19, 5.20 | S15: • Classement des fournisseurs par criticité, évaluation de sécurité avant contrat puis chaque année pour les critiques (5.19) • Clauses de sécurité : notification des incidents sous 48 heures, localisation des données dans l'UE, droit d'audit, réversibilité (5.20) | T15: CFO et RSSI | U15: 30/06/2027 | V15: 3 | W15: 1 | X15: =V15*W15 -> 3 | Y15: =IF(X15>=12,"Critique",IF(X15>=8,"Élevé",IF(X15>=4,"Modéré","Faible"))) -> Faible | Z15: Acceptée par le CFO
A16: R12 | B16: Accès aux données par une autorité étrangère via l'hébergeur (Cloud Act) | C16: Autorité étatique étrangère (droit extraterritorial) | D16: Une autorité américaine contraint AWS à communiquer des données hébergées, sans que NotAge ni ses clients en soient informés. | E16: AP1 à AP3 | F16: AS15 | G16: C | H16: Hébergeur soumis au droit américain ; clés de chiffrement gérées par l'hébergeur | I16: Données hébergées en France ; chiffrement au repos ; engagements contractuels de l'hébergeur | J16: 3 | K16: Question de confiance sensible pour les clients bancaires | L16: 1 | M16: Données de gestion de dépenses sans intérêt particulier pour une autorité étrangère ; cas jamais observé pour ce type de données | N16: =J16*L16 -> 3 | O16: =IF(N16>=12,"Critique",IF(N16>=8,"Élevé",IF(N16>=4,"Modéré","Faible"))) -> Faible | P16: Direction générale (CEO) | Q16: Accepter | R16: Aucune nouvelle mesure | S16: • Aucune nouvelle mesure : risque faible, conforme aux critères d'acceptation • Réponse type préparée pour les clients qui posent la question ; gestion des clés de chiffrement par NotAge étudiable si un client l'exige | T16: Direction générale | U16: Revue annuelle | V16: 3 | W16: 1 | X16: =V16*W16 -> 3 | Y16: =IF(X16>=12,"Critique",IF(X16>=8,"Élevé",IF(X16>=4,"Modéré","Faible"))) -> Faible | Z16: Acceptée par la direction générale

Sheet Cartographie
A1: Cartographie des risques initiaux
A2: Nombre de scénarios par case (calculé depuis la feuille Registre).
A3: Risques initiaux | G3: Risques résiduels (après traitement)
A4: Vraisemblance ↓ / Gravité → | B4: 1 Mineure | C4: 2 Significative | D4: 3 Grave | E4: 4 Critique | G4: Vraisemblance ↓ / Gravité → | H4: 1 Mineure | I4: 2 Significative | J4: 3 Grave | K4: 4 Critique
A5: 4 Quasi certain | B5: =COUNTIFS(Registre!$J$5:$J$16,1,Registre!$L$5:$L$16,4) -> 0 | C5: =COUNTIFS(Registre!$J$5:$J$16,2,Registre!$L$5:$L$16,4) -> 0 | D5: =COUNTIFS(Registre!$J$5:$J$16,3,Registre!$L$5:$L$16,4) -> 0 | E5: =COUNTIFS(Registre!$J$5:$J$16,4,Registre!$L$5:$L$16,4) -> 0 | G5: 4 Quasi certain | H5: =COUNTIFS(Registre!$V$5:$V$16,1,Registre!$W$5:$W$16,4) -> 0 | I5: =COUNTIFS(Registre!$V$5:$V$16,2,Registre!$W$5:$W$16,4) -> 0 | J5: =COUNTIFS(Registre!$V$5:$V$16,3,Registre!$W$5:$W$16,4) -> 0 | K5: =COUNTIFS(Registre!$V$5:$V$16,4,Registre!$W$5:$W$16,4) -> 0
A6: 3 Très vraisemblable | B6: =COUNTIFS(Registre!$J$5:$J$16,1,Registre!$L$5:$L$16,3) -> 0 | C6: =COUNTIFS(Registre!$J$5:$J$16,2,Registre!$L$5:$L$16,3) -> 1 | D6: =COUNTIFS(Registre!$J$5:$J$16,3,Registre!$L$5:$L$16,3) -> 2 | E6: =COUNTIFS(Registre!$J$5:$J$16,4,Registre!$L$5:$L$16,3) -> 3 | G6: 3 Très vraisemblable | H6: =COUNTIFS(Registre!$V$5:$V$16,1,Registre!$W$5:$W$16,3) -> 1 | I6: =COUNTIFS(Registre!$V$5:$V$16,2,Registre!$W$5:$W$16,3) -> 0 | J6: =COUNTIFS(Registre!$V$5:$V$16,3,Registre!$W$5:$W$16,3) -> 0 | K6: =COUNTIFS(Registre!$V$5:$V$16,4,Registre!$W$5:$W$16,3) -> 0
A7: 2 Vraisemblable | B7: =COUNTIFS(Registre!$J$5:$J$16,1,Registre!$L$5:$L$16,2) -> 0 | C7: =COUNTIFS(Registre!$J$5:$J$16,2,Registre!$L$5:$L$16,2) -> 0 | D7: =COUNTIFS(Registre!$J$5:$J$16,3,Registre!$L$5:$L$16,2) -> 3 | E7: =COUNTIFS(Registre!$J$5:$J$16,4,Registre!$L$5:$L$16,2) -> 2 | G7: 2 Vraisemblable | H7: =COUNTIFS(Registre!$V$5:$V$16,1,Registre!$W$5:$W$16,2) -> 0 | I7: =COUNTIFS(Registre!$V$5:$V$16,2,Registre!$W$5:$W$16,2) -> 2 | J7: =COUNTIFS(Registre!$V$5:$V$16,3,Registre!$W$5:$W$16,2) -> 1 | K7: =COUNTIFS(Registre!$V$5:$V$16,4,Registre!$W$5:$W$16,2) -> 1
A8: 1 Peu vraisemblable | B8: =COUNTIFS(Registre!$J$5:$J$16,1,Registre!$L$5:$L$16,1) -> 0 | C8: =COUNTIFS(Registre!$J$5:$J$16,2,Registre!$L$5:$L$16,1) -> 0 | D8: =COUNTIFS(Registre!$J$5:$J$16,3,Registre!$L$5:$L$16,1) -> 1 | E8: =COUNTIFS(Registre!$J$5:$J$16,4,Registre!$L$5:$L$16,1) -> 0 | G8: 1 Peu vraisemblable | H8: =COUNTIFS(Registre!$V$5:$V$16,1,Registre!$W$5:$W$16,1) -> 0 | I8: =COUNTIFS(Registre!$V$5:$V$16,2,Registre!$W$5:$W$16,1) -> 0 | J8: =COUNTIFS(Registre!$V$5:$V$16,3,Registre!$W$5:$W$16,1) -> 4 | K8: =COUNTIFS(Registre!$V$5:$V$16,4,Registre!$W$5:$W$16,1) -> 3
A11: Répartition par zone
A12: Zone | B12: Initial | C12: Résiduel
A13: Critique | B13: =COUNTIF(Registre!$O$5:$O$16,"Critique") -> 3 | C13: =COUNTIF(Registre!$Y$5:$Y$16,"Critique") -> 0
A14: Élevé | B14: =COUNTIF(Registre!$O$5:$O$16,"Élevé") -> 4 | C14: =COUNTIF(Registre!$Y$5:$Y$16,"Élevé") -> 1
A15: Modéré | B15: =COUNTIF(Registre!$O$5:$O$16,"Modéré") -> 4 | C15: =COUNTIF(Registre!$Y$5:$Y$16,"Modéré") -> 6
A16: Faible | B16: =COUNTIF(Registre!$O$5:$O$16,"Faible") -> 1 | C16: =COUNTIF(Registre!$Y$5:$Y$16,"Faible") -> 5
A17: Total | B17: =SUM(B13:B16) -> 12 | C17: =SUM(C13:C16) -> 12

Sheet Mesures prioritaires
A1: Les mesures de l'annexe A retenues pour traiter les scénarios
A2: La déclaration d'applicabilité (NTG-SMSI-DDA-001) examine les 93 mesures ; celles-ci sont les mesures prioritaires du plan de traitement.
A4: Mesure | B4: Intitulé | C4: Scénarios traités | D4: Nombre de scénarios
A5: 5.16 | B5: Gestion des identités | C5: R07 | D5: 1
A6: 5.17 | B6: Informations d'authentification | C6: R05 | D6: 1
A7: 5.18 | B7: Droits d'accès | C7: R02, R07 | D7: 2
A8: 5.19 | B8: Sécurité de l'information dans les relations avec les fournisseurs | C8: R11 | D8: 1
A9: 5.20 | B9: Sécurité de l'information dans les accords avec les fournisseurs | C9: R11 | D9: 1
A10: 5.23 | B10: Sécurité de l'information dans l'utilisation de services en nuage | C10: R04 | D10: 1
A11: 5.24 | B11: Planification et préparation de la gestion des incidents | C11: R02 | D11: 1
A12: 5.26 | B12: Réponse aux incidents de sécurité de l'information | C12: R02 | D12: 1
A13: 5.30 | B13: Préparation des TIC pour la continuité d'activité | C13: R08 | D13: 1
A14: 6.3 | B14: Sensibilisation, enseignement et formation | C14: R09 | D14: 1
A15: 6.5 | B15: Responsabilités après la fin ou la modification du contrat | C15: R07 | D15: 1
A16: 6.8 | B16: Déclaration des événements de sécurité de l'information | C16: R09 | D16: 1
... A32: 8.32 | B32: Gestion des changements | C32: R05, R08 | D32: 2
A33: Total | B33: =COUNTA(A5:A32) -> 28
